[
    {
      "Hakkelademands leksikon Afsnit nr.": 1,
      "Filmtitel": "Hercules i New York",
      "Fed skurk": 1,
      "Bar hud/Store muskler": 9,
      "Vilde våben": 1,
      "Stærke oneliners": 2,
      "Episk action": 2,
      "Total": 15
    },
    {
      "Hakkelademands leksikon Afsnit nr.": 2,
      "Filmtitel": "Assassins",
      "Fed skurk": 8,
      "Bar hud/Store muskler": 1,
      "Vilde våben": 7,
      "Stærke oneliners": 6,
      "Episk action": 5,
      "Total": 27
    },
    {
      "Hakkelademands leksikon Afsnit nr.": 3,
      "Filmtitel": "Commando",
      "Fed skurk": 5,
      "Bar hud/Store muskler": 9,
      "Vilde våben": 10,
      "Stærke oneliners": 9,
      "Episk action": 10,
      "Total": 43
    },
    {
      "Hakkelademands leksikon Afsnit nr.": 4,
      "Filmtitel": "Cyborg",
      "Fed skurk": 4,
      "Bar hud/Store muskler": 6,
      "Vilde våben": 6,
      "Stærke oneliners": 2,
      "Episk action": 6,
      "Total": 47
    },
    {
      "Hakkelademands leksikon Afsnit nr.": 5,
      "Filmtitel": "Kapring på åbent hav",
      "Fed skurk": 4,
      "Bar hud/Store muskler": 5,
      "Vilde våben": 5,
      "Stærke oneliners": 2,
      "Episk action": 5,
      "Total": 21
    },
    {
      "Hakkelademands leksikon Afsnit nr.": 6,
      "Filmtitel": "Demolition man",
      "Fed skurk": 9,
      "Bar hud/Store muskler": 7,
      "Vilde våben": 7,
      "Stærke oneliners": 8,
      "Episk action": 9,
      "Total": 40
    },
    {
      "Hakkelademands leksikon Afsnit nr.": 7,
      "Filmtitel": "True Lies",
      "Fed skurk": 6,
      "Bar hud/Store muskler": 5,
      "Vilde våben": 10,
      "Stærke oneliners": 8,
      "Episk action": 8,
      "Total": 37
    },
    {
      "Hakkelademands leksikon Afsnit nr.": 8,
      "Filmtitel": "Road House",
      "Fed skurk": 6,
      "Bar hud/Store muskler": 8,
      "Vilde våben": 2,
      "Stærke oneliners": 7,
      "Episk action": 7,
      "Total": 30
    },
    {
      "Hakkelademands leksikon Afsnit nr.": 9,
      "Filmtitel": "Cobra",
      "Fed skurk": 7,
      "Bar hud/Store muskler": 2,
      "Vilde våben": 9,
      "Stærke oneliners": 8,
      "Episk action": 8,
      "Total": 34
    },
    {
      "Hakkelademands leksikon Afsnit nr.": 10,
      "Filmtitel": "Sudden Death",
      "Fed skurk": 7,
      "Bar hud/Store muskler": 1,
      "Vilde våben": 4,
      "Stærke oneliners": 4,
      "Episk action": 4,
      "Total": 20
    },
    {
      "Hakkelademands leksikon Afsnit nr.": 11,
      "Filmtitel": "Barb Wire",
      "Fed skurk": 2,
      "Bar hud/Store muskler": 10,
      "Vilde våben": 6,
      "Stærke oneliners": 2,
      "Episk action": 3,
      "Total": 41
    },
    {
      "Hakkelademands leksikon Afsnit nr.": 12,
      "Filmtitel": "Con Air",
      "Fed skurk": 10,
      "Bar hud/Store muskler": 7,
      "Vilde våben": 4,
      "Stærke oneliners": 9,
      "Episk action": 8,
      "Total": 38
    },
    {
      "Hakkelademands leksikon Afsnit nr.": 13,
      "Filmtitel": "Showdown in Little Tokyo",
      "Fed skurk": 8,
      "Bar hud/Store muskler": 9,
      "Vilde våben": 7,
      "Stærke oneliners": 7,
      "Episk action": 8,
      "Total": 39
    },
    {
      "Hakkelademands leksikon Afsnit nr.": 14,
      "Filmtitel": "Platoon Leader",
      "Fed skurk": 1,
      "Bar hud/Store muskler": 1,
      "Vilde våben": 6,
      "Stærke oneliners": 1,
      "Episk action": 2,
      "Total": 11
    },
    {
      "Hakkelademands leksikon Afsnit nr.": 15,
      "Filmtitel": "Predator",
      "Fed skurk": 10,
      "Bar hud/Store muskler": 10,
      "Vilde våben": 10,
      "Stærke oneliners": 10,
      "Episk action": 9,
      "Total": 49
    },
    {
      "Hakkelademands leksikon Afsnit nr.": 16,
      "Filmtitel": "Jingle all the way",
      "Fed skurk": 4,
      "Bar hud/Store muskler": 1,
      "Vilde våben": 4,
      "Stærke oneliners": 5,
      "Episk action": 4,
      "Bonus kategorier": "8 (julestemning)",
      "Total": 18
    },
    {
      "Hakkelademands leksikon Afsnit nr.": 17,
      "Filmtitel": "Bloodsport",
      "Fed skurk": 9,
      "Bar hud/Store muskler": 10,
      "Vilde våben": 2,
      "Stærke oneliners": 5,
      "Episk action": 10,
      "Total": 36
    },
    {
      "Hakkelademands leksikon Afsnit nr.": 18,
      "Filmtitel": "Hard Ticket to Hawaii",
      "Fed skurk": 5,
      "Bar hud/Store muskler": 10,
      "Vilde våben": 7,
      "Stærke oneliners": 4,
      "Episk action": 5,
      "Total": 31
    },
    {
      "Hakkelademands leksikon Afsnit nr.": 19,
      "Filmtitel": "Stone Cold",
      "Fed skurk": 8,
      "Bar hud/Store muskler": 7,
      "Vilde våben": 5,
      "Stærke oneliners": 4,
      "Episk action": 6,
      "Total": 30
    },
    {
      "Hakkelademands leksikon Afsnit nr.": 20,
      "Filmtitel": "Rocky IV",
      "Fed skurk": 8,
      "Store muskler": 10,
      "Vilde våben": 3,
      "Stærke oneliners": 4,
      "Total": 25
    },
    {
      "Hakkelademands leksikon Afsnit nr.": 21,
      "Filmtitel": "Nico / Above the Law",
      "Fed skurk": 2,
      "Vilde våben": 4,
      "Stærke oneliners": 4,
      "Total": 10
    },
    {
      "Hakkelademands leksikon Afsnit nr.": 22,
      "Filmtitel": "Delta Force",
      "Fed skurk": 5,
      "Vilde våben": 10,
      "Stærke oneliners": 2,
      "Total": 17
    },
    {
      "Hakkelademands leksikon Afsnit nr.": 23,
      "Filmtitel": "Action Jackson",
      "Fed skurk": 4,
      "Store muskler": 6,
      "Bar hud": 6,
      "Vilde våben": 5,
      "Stærke oneliners": 7,
      "Total": 28
    },
    {
      "Hakkelademands leksikon Afsnit nr.": 24,
      "Filmtitel": "Red Heat",
      "Fed skurk": 5,
      "Store muskler": 7,
      "Bar hud": 6,
      "Vilde våben": 5,
      "Stærke oneliners": 4,
      "Total": 27
    },
    {
      "Hakkelademands leksikon Afsnit nr.": 25,
      "Filmtitel": "Blade",
      "Fed skurk": 8,
      "Store muskler": 6,
      "Bar hud": 1,
      "Vilde våben": 10,
      "Stærke oneliners": 9,
      "Total": 34
    },
    {
      "Hakkelademands leksikon Afsnit nr.": 26,
      "Filmtitel": "Timecop",
      "Fed skurk": 3,
      "Store muskler": 7,
      "Bar hud": 7,
      "Vilde våben": 7,
      "Stærke oneliners": 5,
      "Total": 45
    },
    {
      "Hakkelademands leksikon Afsnit nr.": 27,
      "Filmtitel": "Die Hard",
      "Fed skurk": 10,
      "Store muskler": 6,
      "Bar hud": 5,
      "Vilde våben": 10,
      "Stærke oneliners": 10,
      "Bonus kategorier": "6 (julestemning)",
      "Total": 41
    },
    {
      "Hakkelademands leksikon Afsnit nr.": 28,
      "Filmtitel": "Tango and Cash",
      "Fed skurk": 4,
      "Store muskler": 8,
      "Bar hud": 4,
      "Vilde våben": 8,
      "Stærke oneliners": 8,
      "Total": 32
    },
    {
      "Hakkelademands leksikon Afsnit nr.": 29,
      "Filmtitel": "Top Dog",
      "Fed skurk": 1,
      "Store muskler": 1,
      "Vilde våben": 4,
      "Stærke oneliners": 2,
      "Total": 8
    },
    {
      "Hakkelademands leksikon Afsnit nr.": 30,
      "Filmtitel": "The Matrix",
      "Fed skurk": 10,
      "Store muskler": 3,
      "Bar hud": 2,
      "Vilde våben": 10,
      "Stærke oneliners": 10,
      "Total": 35
    },
    {
      "Hakkelademands leksikon Afsnit nr.": 31,
      "Filmtitel": "John Wick",
      "Fed skurk": 9,
      "Store muskler": 3,
      "Bar hud": 1,
      "Vilde våben": 9,
      "Stærke oneliners": 7,
      "Total": 29
    },
    {
      "Hakkelademands leksikon Afsnit nr.": 32,
      "Filmtitel": "Rapid Fire (Ildkamp)",
      "Fed skurk": 8,
      "Store muskler": 6,
      "Bar hud": 4,
      "Vilde våben": 7,
      "Stærke oneliners": 5,
      "Total": 30
    },
    {
      "Hakkelademands leksikon Afsnit nr.": 33,
      "Filmtitel": "Desperado",
      "Fed skurk": 9,
      "Store muskler": 4,
      "Bar hud": 10,
      "Vilde våben": 10,
      "Stærke oneliners": 6,
      "Total": 39
    },
    {
      "Hakkelademands leksikon Afsnit nr.": 34,
      "Filmtitel": "The Fast and the Furious",
      "Fed skurk": 7,
      "Store muskler": 5,
      "Bar hud": 3,
      "Vilde våben": 3,
      "Stærke oneliners": 6,
      "Total": 24
    },
    {
      "Hakkelademands leksikon Afsnit nr.": 35,
      "Filmtitel": "Face/Off"
    },
    {
      "Hakkelademands leksikon Afsnit nr.": 36,
      "Filmtitel": "Universal Soldier",
      "Fed skurk": 8,
      "Store muskler": 10,
      "Vilde våben": 8,
      "Stærke oneliners": 6,
      "Total": 32
    },
    {
      "Hakkelademands leksikon Afsnit nr.": 37,
      "Filmtitel": "Lone Wolf McQuade",
      "Fed skurk": 6,
      "Store muskler": 4,
      "Vilde våben": 7,
      "Stærke oneliners": 3,
      "Total": 20
    },
    {
      "Hakkelademands leksikon Afsnit nr.": 38,
      "Filmtitel": "Enter the Dragon ",
      "Fed skurk": 9,
      "Store muskler": 8,
      "Bar hud": 5,
      "Vilde våben": 6,
      "Stærke oneliners": 10,
      "Total": 38
    },
    {
      "Hakkelademands leksikon Afsnit nr.": 39,
      "Filmtitel": "Starship Troopers",
      "Fed skurk": 9,
      "Store muskler": 5,
      "Bar hud": 6,
      "Vilde våben": 8,
      "Stærke oneliners": 9,
      "Total": 37
    },
    {
      "Hakkelademands leksikon Afsnit nr.": 40,
      "Filmtitel": "Mortal Kombat",
      "Fed skurk": 8,
      "Store muskler": 9,
      "Bar hud": 1,
      "Vilde våben": 7,
      "Stærke oneliners": 8,
      "Total": 33
    },
    {
      "Hakkelademands leksikon Afsnit nr.": 41,
      "Filmtitel": "The Rock",
      "Fed skurk": 10,
      "Store muskler": 2,
      "Bar hud": 1,
      "Vilde våben": 10,
      "Stærke oneliners": 9,
      "Total": 32
    },
    {
      "Hakkelademands leksikon Afsnit nr.": 42,
      "Filmtitel": "Total Recall",
      "Fed skurk": 8,
      "Store muskler": 8,
      "Bar hud": 8,
      "Vilde våben": 9,
      "Stærke oneliners": 10,
      "Total": 43
    },
    {
      "Hakkelademands leksikon Afsnit nr.": 43,
      "Filmtitel": "Rambo III",
      "Fed skurk": 6,
      "Store muskler": 10,
      "Vilde våben": 9,
      "Stærke oneliners": 7,
      "Bonus kategorier": "9 (lækkert hår)",
      "Total": 32
    },
    {
      "Hakkelademands leksikon Afsnit nr.": 44,
      "Filmtitel": "Kickboxer",
      "Fed skurk": 6,
      "Store muskler": 10,
      "Bar hud": 5,
      "Vilde våben": 5,
      "Stærke oneliners": 1,
      "Total": 27
    },
    {
      "Hakkelademands leksikon Afsnit nr.": 45,
      "Filmtitel": "Lethal Weapons",
      "Fed skurk": 10,
      "Store muskler": 7,
      "Bar hud": 5,
      "Vilde våben": 4,
      "Stærke oneliners": 10,
      "Bonus kategorier": "10 (jul) / 9 (hår)",
      "Total": 55
    },
    {
      "Hakkelademands leksikon Afsnit nr.": 46,
      "Filmtitel": "Atomic Blonde",
      "Fed skurk": 5,
      "Store muskler": 1,
      "Bar hud": 5,
      "Vilde våben": 3,
      "Stærke oneliners": 2,
      "Total": 16
    },
    {
      "Hakkelademands leksikon Afsnit nr.": 47,
      "Filmtitel": "Passenger 57",
      "Fed skurk": 8,
      "Store muskler": 3,
      "Vilde våben": 3,
      "Stærke oneliners": 10,
      "Bonus kategorier": "6 (lækkert hår)",
      "Total": 24
    },
    {
      "Hakkelademands leksikon Afsnit nr.": 48,
      "Filmtitel": "Eraser",
      "Fed skurk": 7,
      "Store muskler": 4,
      "Vilde våben": 9,
      "Stærke oneliners": 8,
      "Total": 28
    },
    {
      "Hakkelademands leksikon Afsnit nr.": 49,
      "Filmtitel": "Cliffhanger",
      "Fed skurk": 8,
      "Store muskler": 10,
      "Vilde våben": 4,
      "Stærke oneliners": 7,
      "Total": 29
    },
    {
      "Hakkelademands leksikon Afsnit nr.": 50,
      "Filmtitel": "Aliens",
      "Fed skurk": 10,
      "Store muskler": 4,
      "Bar hud": 3,
      "Vilde våben": 10,
      "Stærke oneliners": 10,
      "Total": 37
    },
    {
      "Hakkelademands leksikon Afsnit nr.": 51,
      "Filmtitel": "Pacific Rim",
      "Fed skurk": 7,
      "Store muskler": 4,
      "Bar hud": 1,
      "Vilde våben": 10,
      "Stærke oneliners": 3,
      "Total": 25
    },
    {
      "Hakkelademands leksikon Afsnit nr.": 52,
      "Filmtitel": "Death Warrant",
      "Fed skurk": 7,
      "Bar hud/Store muskler": 7,
      "Vilde våben": 3,
      "Stærke oneliners": 3,
      "Episk action": 6,
      "Total": 26
    },
    {
      "Hakkelademands leksikon Afsnit nr.": 53,
      "Filmtitel": "Speed",
      "Fed skurk": 6,
      "Bar hud/Store muskler": 3,
      "Vilde våben": 3,
      "Stærke oneliners": 8,
      "Episk action": 7,
      "Total": 27
    },
    {
      "Hakkelademands leksikon Afsnit nr.": 54,
      "Filmtitel": "Point Break"
    },
    {
      "Hakkelademands leksikon Afsnit nr.": 55,
      "Filmtitel": "Conan the Barbarian",
      "Fed skurk": 8,
      "Bar hud/Store muskler": 10,
      "Vilde våben": 10,
      "Stærke oneliners": 2,
      "Episk action": 8,
      "Total": 38
    },
    {
      "Hakkelademands leksikon Afsnit nr.": 56,
      "Filmtitel": "The Expendables",
      "Fed skurk": 6,
      "Bar hud/Store muskler": 8,
      "Vilde våben": 9,
      "Stærke oneliners": 7,
      "Episk action": 8,
      "Total": 38
    },
    {
      "Hakkelademands leksikon Afsnit nr.": 57,
      "Filmtitel": "Broken Arrow",
      "Fed skurk": 10,
      "Bar hud/Store muskler": 1,
      "Vilde våben": 8,
      "Stærke oneliners": 9,
      "Episk action": 9,
      "Total": 37
    },
    {
      "Hakkelademands leksikon Afsnit nr.": 58,
      "Filmtitel": "Double Team",
      "Fed skurk": 4,
      "Bar hud/Store muskler": 7,
      "Vilde våben": 9,
      "Stærke oneliners": 1,
      "Episk action": 8,
      "Total": 29
    },
    {
      "Hakkelademands leksikon Afsnit nr.": 59,
      "Filmtitel": "Bad Boys",
      "Fed skurk": 6,
      "Bar hud/Store muskler": 8,
      "Vilde våben": 7,
      "Stærke oneliners": 10,
      "Episk action": 7,
      "Total": 38
    },
    {
      "Hakkelademands leksikon Afsnit nr.": 60,
      "Filmtitel": "Taken",
      "Fed skurk": 4,
      "Bar hud/Store muskler": 1,
      "Vilde våben": 5,
      "Stærke oneliners": 7,
      "Episk action": 5,
      "Total": 22
    },
    {
      "Hakkelademands leksikon Afsnit nr.": 61,
      "Filmtitel": "The Running Man",
      "Fed skurk": 10,
      "Bar hud/Store muskler": 9,
      "Vilde våben": 8,
      "Stærke oneliners": 9,
      "Episk action": 8,
      "Total": 44
    },
    {
      "Hakkelademands leksikon Afsnit nr.": 62,
      "Filmtitel": "Waterworld",
      "Fed skurk": 7,
      "Bar hud/Store muskler": 2,
      "Vilde våben": 8,
      "Stærke oneliners": 2,
      "Episk action": 8,
      "Total": 27
    },
    {
      "Hakkelademands leksikon Afsnit nr.": 63,
      "Filmtitel": "Rambo: First Blood Part II",
      "Fed skurk": 7,
      "Bar hud/Store muskler": 10,
      "Vilde våben": 10,
      "Stærke oneliners": 7,
      "Episk action": 9,
      "Total": 43
    },
    {
      "Hakkelademands leksikon Afsnit nr.": 64,
      "Filmtitel": "The Rundown",
      "Fed skurk": 3,
      "Bar hud/Store muskler": 9,
      "Vilde våben": 7,
      "Stærke oneliners": 3,
      "Episk action": 7,
      "Total": 29
    },
    {
      "Hakkelademands leksikon Afsnit nr.": 65,
      "Filmtitel": "Nowhere to Run",
      "Fed skurk": 2,
      "Bar hud/Store muskler": 9,
      "Vilde våben": 3,
      "Stærke oneliners": 4,
      "Episk action": 4,
      "Total": 22
    },
    {
      "Hakkelademands leksikon Afsnit nr.": 66,
      "Filmtitel": "The Punisher (1989)",
      "Fed skurk": 9,
      "Bar hud/Store muskler": 6,
      "Vilde våben": 10,
      "Stærke oneliners": 3,
      "Episk action": 7,
      "Total": 35
    },
    {
      "Hakkelademands leksikon Afsnit nr.": 67,
      "Filmtitel": "Rush Hour",
      "Fed skurk": 5,
      "Vilde våben": 7,
      "Stærke oneliners": 7,
      "Episk action": 8,
      "Total": 27
    },
    {
      "Hakkelademands leksikon Afsnit nr.": 68,
      "Filmtitel": "End of Days",
      "Fed skurk": 9,
      "Bar hud/Store muskler": 6,
      "Vilde våben": 7,
      "Stærke oneliners": 6,
      "Episk action": 6,
      "Total": 26
    },
    {
      "Hakkelademands leksikon Afsnit nr.": 69,
      "Filmtitel": "RoboCop",
      "Fed skurk": 10,
      "Bar hud/Store muskler": 3,
      "Vilde våben": 10,
      "Stærke oneliners": 8,
      "Episk action": 9,
      "Total": 40
    },
    {
      "Hakkelademands leksikon Afsnit nr.": 70,
      "Filmtitel": "Under Siege 2: Dark Territory",
      "Fed skurk": 5,
      "Bar hud/Store muskler": 4,
      "Vilde våben": 5,
      "Stærke oneliners": 5,
      "Episk action": 4,
      "Total": 23
    },
    {
      "Hakkelademands leksikon Afsnit nr.": 71,
      "Filmtitel": "Training Day",
      "Fed skurk": 10,
      "Bar hud/Store muskler": 6,
      "Vilde våben": 7,
      "Stærke oneliners": 10,
      "Episk action": 3,
      "Total": 36
    },
    {
      "Hakkelademands leksikon Afsnit nr.": 72,
      "Filmtitel": "Hard Target",
      "Fed skurk": 9,
      "Bar hud/Store muskler": 6,
      "Vilde våben": 10,
      "Stærke oneliners": 6,
      "Episk action": 10,
      "Total": 41
    },
    {
      "Hakkelademands leksikon Afsnit nr.": 73,
      "Filmtitel": "Top Gun",
      "Fed skurk": 1,
      "Bar hud/Store muskler": 8,
      "Vilde våben": 7,
      "Stærke oneliners": 10,
      "Episk action": 6,
      "Total": 32
    },
    {
      "Hakkelademands leksikon Afsnit nr.": 74,
      "Filmtitel": "The Fifth Element",
      "Fed skurk": 10,
      "Bar hud/Store muskler": 8,
      "Vilde våben": 10,
      "Stærke oneliners": 9,
      "Episk action": 5,
      "Total": 30
    },
    {
      "Hakkelademands leksikon Afsnit nr.": 75,
      "Filmtitel": "The Expendables 2",
      "Fed skurk": 8,
      "Bar hud/Store muskler": 6,
      "Vilde våben": 9,
      "Stærke oneliners": 7,
      "Episk action": 10,
      "Total": 40
    },
    {
      "Hakkelademands leksikon Afsnit nr.": 76,
      "Filmtitel": "Street Fighter",
      "Fed skurk": 9,
      "Bar hud/Store muskler": 8,
      "Vilde våben": 5,
      "Stærke oneliners": 8,
      "Episk action": 2,
      "Total": 32
    },
    {
      "Hakkelademands leksikon Afsnit nr.": 77,
      "Filmtitel": "Kill Bill: Vol. 1",
      "Fed skurk": 10,
      "Bar hud/Store muskler": 4,
      "Vilde våben": 9,
      "Stærke oneliners": 10,
      "Episk action": 10,
      "Total": 43
    },
    {
      "Hakkelademands leksikon Afsnit nr.": 78,
      "Filmtitel": "Kill Bill: Vol. 2",
      "Fed skurk": 10,
      "Bar hud/Store muskler": 3,
      "Vilde våben": 7,
      "Stærke oneliners": 10,
      "Episk action": 9,
      "Total": 39
    },
    {
      "Hakkelademands leksikon Afsnit nr.": 79,
      "Filmtitel": "Escape Plan",
      "Fed skurk": 3,
      "Bar hud/Store muskler": 2,
      "Vilde våben": 4,
      "Stærke oneliners": 4,
      "Episk action": 4,
      "Total": 17
    },
    {
      "Hakkelademands leksikon Afsnit nr.": 80,
      "Filmtitel": "The Three Musketeers",
      "Fed skurk": 9,
      "Bar hud/Store muskler": 7,
      "Vilde våben": 8,
      "Stærke oneliners": 9,
      "Episk action": 7,
      "Total": 40
    },
    {
      "Hakkelademands leksikon Afsnit nr.": 81,
      "Filmtitel": "Collateral",
      "Fed skurk": 10,
      "Bar hud/Store muskler": 1,
      "Vilde våben": 7,
      "Stærke oneliners": 10,
      "Episk action": 8,
      "Total": 36
    },
    {
      "Hakkelademands leksikon Afsnit nr.": 82,
      "Filmtitel": "Robin Hood: Prince of Thieves",
      "Fed skurk": 10,
      "Bar hud/Store muskler": 3,
      "Vilde våben": 9,
      "Stærke oneliners": 9,
      "Episk action": 8,
      "Total": 39
    },
    {
      "Hakkelademands leksikon Afsnit nr.": 83,
      "Filmtitel": "Freddy vs. Jason",
      "Fed skurk": 7,
      "Bar hud/Store muskler": 7,
      "Vilde våben": 7,
      "Stærke oneliners": 2,
      "Episk action": 7,
      "Total": 30
    },
    {
      "Hakkelademands leksikon Afsnit nr.": 84,
      "Filmtitel": "Shanghai Noon",
      "Fed skurk": 6,
      "Bar hud/Store muskler": 6,
      "Vilde våben": 8,
      "Stærke oneliners": 8,
      "Episk action": 9,
      "Total": 37
    },
    {
      "Hakkelademands leksikon Afsnit nr.": 85,
      "Filmtitel": "Man on Fire",
      "Fed skurk": 6,
      "Bar hud/Store muskler": 2,
      "Vilde våben": 8,
      "Stærke oneliners": 6,
      "Episk action": 2,
      "Total": 24
    },
    {
      "Hakkelademands leksikon Afsnit nr.": 86,
      "Filmtitel": "Blade II",
      "Fed skurk": 9,
      "Bar hud/Store muskler": 6,
      "Vilde våben": 10,
      "Stærke oneliners": 3,
      "Episk action": 8,
      "Total": 36
    },
    {
      "Hakkelademands leksikon Afsnit nr.": 87,
      "Filmtitel": "The Long Kiss Goodnight",
      "Fed skurk": 8,
      "Bar hud/Store muskler": 3,
      "Vilde våben": 9,
      "Stærke oneliners": 10,
      "Episk action": 8,
      "Bonus kategorier": "7 (julestemning)",
      "Total": 38
    },
    {
      "Hakkelademands leksikon Afsnit nr.": 88,
      "Filmtitel": "Maximum Risk",
      "Fed skurk": 3,
      "Bar hud/Store muskler": 9,
      "Vilde våben": 2,
      "Stærke oneliners": 3,
      "Episk action": 6,
      "Total": 23
    },
    {
      "Hakkelademands leksikon Afsnit nr.": 89,
      "Filmtitel": "The Terminator",
      "Fed skurk": 10,
      "Bar hud/Store muskler": 9,
      "Vilde våben": 10,
      "Stærke oneliners": 10,
      "Episk action": 9,
      "Total": 48
    },
    {
      "Hakkelademands leksikon Afsnit nr.": 90,
      "Filmtitel": "The Mask of Zorro",
      "Fed skurk": 7,
      "Bar hud/Store muskler": 7,
      "Vilde våben": 5,
      "Stærke oneliners": 8,
      "Episk action": 9,
      "Total": 36
    },
    {
      "Hakkelademands leksikon Afsnit nr.": 91,
      "Filmtitel": "The Bourne Identity",
      "Fed skurk": 7,
      "Bar hud/Store muskler": 2,
      "Vilde våben": 7,
      "Stærke oneliners": 4,
      "Episk action": 8,
      "Total": 28
    },
    {
      "Hakkelademands leksikon Afsnit nr.": 92,
      "Filmtitel": "Lara Croft: Tomb Raider",
      "Fed skurk": 6,
      "Bar hud/Store muskler": 8,
      "Vilde våben": 7,
      "Stærke oneliners": 2,
      "Episk action": 6,
      "Total": 29
    },
    {
      "Hakkelademands leksikon Afsnit nr.": 93
    },
    {
      "Hakkelademands leksikon Afsnit nr.": 94
    },
    {
      "Hakkelademands leksikon Afsnit nr.": 95
    }
  ]